LICENSE
MANIFEST.in
setup.py
cloudfs/__init__.py
cloudfs/account.py
cloudfs/container.py
cloudfs/errors.py
cloudfs/file.py
cloudfs/filesystem.py
cloudfs/item.py
cloudfs/media.py
cloudfs/path.py
cloudfs/session.py
cloudfs/share.py
cloudfs/user.py
cloudfs/private/__init__.py
cloudfs/private/cached_object.py
cloudfs/private/cloudfs_paths.py
cloudfs/private/filesystem_common.py
cloudfs/private/rest_api_adapter.py
cloudfs/private/utils.py
cloudfs_sdk.egg-info/PKG-INFO
cloudfs_sdk.egg-info/SOURCES.txt
cloudfs_sdk.egg-info/dependency_links.txt
cloudfs_sdk.egg-info/pbr.json
cloudfs_sdk.egg-info/requires.txt
cloudfs_sdk.egg-info/top_level.txt
test/test_account.py
test/test_authentication.py
test/test_errors.py
test/test_file.py
test/test_filesystem.py
test/test_folder.py
test/test_path.py
test/test_settings.py
test/test_share.py
test/test_trash.py
test/test_user.py