Metadata-Version: 1.1
Name: cloudfs-sdk
Version: 1.0.1
Summary: Python SDK for CloudFS cloud storage file system.
Home-page: https://www.bitcasa.com/cloudfs
Author: Bitcasa Inc.
Author-email: drex@bitcasa.com
License: MIT
Keywords: cloud storage filesystem
Platform: UNKNOWN
Classifier: Development Status :: 4 - Beta
Classifier: Intended Audience :: Developers
Classifier: License :: OSI Approved :: MIT License
Classifier: Programming Language :: Python
Classifier: Programming Language :: Python :: 2
Classifier: Programming Language :: Python :: 2.7
Classifier: Topic :: Other/Nonlisted Topic
